Makefile
setup.py
docs/source/HISTORY.rst
docs/source/README.rst
xmldirector/__init__.py
xmldirector.dita.egg-info/PKG-INFO
xmldirector.dita.egg-info/SOURCES.txt
xmldirector.dita.egg-info/dependency_links.txt
xmldirector.dita.egg-info/entry_points.txt
xmldirector.dita.egg-info/namespace_packages.txt
xmldirector.dita.egg-info/not-zip-safe
xmldirector.dita.egg-info/requires.txt
xmldirector.dita.egg-info/top_level.txt
xmldirector/dita/__init__.py
xmldirector/dita/converter.py
xmldirector/dita/header.txt
xmldirector/dita/html2dita.py
xmldirector/dita/install.py
xmldirector/dita/logger.py
xmldirector/dita/util.py
xmldirector/dita/converters/__init__.py
xmldirector/dita/converters/h2d/__init__.py
xmldirector/dita/converters/h2d/h2d.xsl