Metadata-Version: 1.1
Name: xmldirector.dita
Version: 0.0.17
Summary: XML-Director DITA conversion
Home-page: http://pypi.python.org/pypi/xmldirector.dita
Author: Andreas Jung
Author-email: info@zopyx.com
License: GPL
Keywords: xml-director DOCX XML C-Rex Plone Python DITA
Platform: UNKNOWN
Classifier: Programming Language :: Python
Classifier: Framework :: Plone
Classifier: Framework :: Plone :: 4.3
Classifier: Framework :: Plone :: 5.0
Classifier: Framework :: Zope2
Classifier: Topic :: Software Development :: Libraries :: Python Modules
